qthreadwithreturn/__init__.py
qthreadwithreturn/qthread_pool_executor.py
qthreadwithreturn/qthread_with_return.py
qthreadwithreturn-1.6.19.dist-info/licenses/LICENSE
qthreadwithreturn-1.6.19.dist-info/METADATA
qthreadwithreturn-1.6.19.dist-info/WHEEL
qthreadwithreturn-1.6.19.dist-info/top_level.txt
qthreadwithreturn-1.6.19.dist-info/RECORD
