Metadata-Version: 2.4
Name: qthreadwithreturn
Version: 1.6.19
Summary: PySide6 高级线程工具库 - 带返回值的线程类和线程池执行器
Author-email: PythonImporter <271374667@qq.com>
Maintainer-email: PythonImporter <271374667@qq.com>
License-Expression: MIT
Project-URL: Homepage, https://github.com/271374667/QThreadWithReturn
Project-URL: Repository, https://github.com/271374667/QThreadWithReturn.git
Project-URL: Issues, https://github.com/271374667/QThreadWithReturn/issues
Keywords: qt,pyside6,threading,concurrent,futures,gui,pyqt,async,thread-pool,worker-thread
Classifier: Programming Language :: Python :: 3
Classifier: Programming Language :: Python :: 3.10
Classifier: Programming Language :: Python :: 3.11
Classifier: Programming Language :: Python :: 3.12
Classifier: Programming Language :: Python :: 3.13
Requires-Python: >=3.10
License-File: LICENSE
Requires-Dist: pyside6>=6.4.0
Dynamic: license-file
